Workbook

Sheet Dataset
A1: PR. 2 Analyzer - Sales Dataset
A2: Customer_ID | B2: Customer_Name | C2: Region | D2: Product_Category | E2: Sales | F2: Quantity | G2: Discount | H2: Order_Date | I2: Profit | J2: Total_Purchase | K2: Month | L2: Monthly_Sales | M2: Growth_Icon | N2: Timestamp | O2: Customer_Rank
A3: CUST014 | B3: Emma Davis | C3: West | D3: Books | E3: 716.88 | F3: 7 | G3: 0.15 | H3: 45392 | I3: 348.83 | J3: =E3*F3*(1-G3) -> 4265.436 | K3: =TEXT(H3,"mmm-yyyy") -> Apr-2024 | L3: =SUMIFS($J:$J,$K:$K,K3) -> 191711.31 | M3: ="►" -> ► | N3: =NOW() -> 46283.658 | O3: =RANK(J3,$J$3:$J$82,0) -> 59
A4: CUST001 | B4: Linda Wilson | C4: West | D4: Furniture | E4: 1478.05 | F4: 7 | G4: 0.15 | H4: 45392 | I4: 733.78 | J4: =E4*F4*(1-G4) -> 8794.3975 | K4: =TEXT(H4,"mmm-yyyy") -> Apr-2024 | L4: =SUMIFS($J:$J,$K:$K,K4) -> 191711.31 | M4: =IF(L4>L3,"▲",IF(L4<L3,"▼","►")) -> ► | N4: =NOW() -> 46283.658 | O4: =RANK(J4,$J$3:$J$82,0) -> 30
A5: CUST026 | B5: Mary Davis | C5: East | D5: Clothing | E5: 1570.26 | F5: 7 | G5: 0.15 | H5: 45395 | I5: 383.24 | J5: =E5*F5*(1-G5) -> 9343.047 | K5: =TEXT(H5,"mmm-yyyy") -> Apr-2024 | L5: =SUMIFS($J:$J,$K:$K,K5) -> 191711.31 | M5: =IF(L5>L4,"▲",IF(L5<L4,"▼","►")) -> ► | N5: =NOW() -> 46283.658 | O5: =RANK(J5,$J$3:$J$82,0) -> 29
A6: CUST008 | B6: John Brown | C6: South | D6: Electronics | E6: 731.49 | F6: 9 | G6: 0.05 | H6: 45395 | I6: 414.77 | J6: =E6*F6*(1-G6) -> 6254.2395 | K6: =TEXT(H6,"mmm-yyyy") -> Apr-2024 | L6: =SUMIFS($J:$J,$K:$K,K6) -> 191711.31 | M6: =IF(L6>L5,"▲",IF(L6<L5,"▼","►")) -> ► | N6: =NOW() -> 46283.658 | O6: =RANK(J6,$J$3:$J$82,0) -> 46
A7: CUST017 | B7: James Taylor | C7: East | D7: Furniture | E7: 1360.03 | F7: 19 | G7: 0 | H7: 45398 | I7: 1702.95 | J7: =E7*F7*(1-G7) -> 25840.57 | K7: =TEXT(H7,"mmm-yyyy") -> Apr-2024 | L7: =SUMIFS($J:$J,$K:$K,K7) -> 191711.31 | M7: =IF(L7>L6,"▲",IF(L7<L6,"▼","►")) -> ► | N7: =NOW() -> 46283.658 | O7: =RANK(J7,$J$3:$J$82,0) -> 1
A8: CUST012 | B8: Robert Anderson | C8: West | D8: Office Supplies | E8: 945.99 | F8: 18 | G8: 0.05 | H8: 45399 | I8: 1328.83 | J8: =E8*F8*(1-G8) -> 16176.429 | K8: =TEXT(H8,"mmm-yyyy") -> Apr-2024 | L8: =SUMIFS($J:$J,$K:$K,K8) -> 191711.31 | M8: =IF(L8>L7,"▲",IF(L8<L7,"▼","►")) -> ► | N8: =NOW() -> 46283.658 | O8: =RANK(J8,$J$3:$J$82,0) -> 12
A9: CUST026 | B9: Mary Davis | C9: East | D9: Books | E9: 438.74 | F9: 3 | G9: 0.05 | H9: 45400 | I9: 99.07 | J9: =E9*F9*(1-G9) -> 1250.409 | K9: =TEXT(H9,"mmm-yyyy") -> Apr-2024 | L9: =SUMIFS($J:$J,$K:$K,K9) -> 191711.31 | M9: =IF(L9>L8,"▲",IF(L9<L8,"▼","►")) -> ► | N9: =NOW() -> 46283.658 | O9: =RANK(J9,$J$3:$J$82,0) -> 79
A10: CUST030 | B10: James Wilson | C10: North | D10: Books | E10: 407.77 | F10: 17 | G10: 0.2 | H10: 45401 | I10: 308.05 | J10: =E10*F10*(1-G10) -> 5545.672 | K10: =TEXT(H10,"mmm-yyyy") -> Apr-2024 | L10: =SUMIFS($J:$J,$K:$K,K10) -> 191711.31 | M10: =IF(L10>L9,"▲",IF(L10<L9,"▼","►")) -> ► | N10: =NOW() -> 46283.658 | O10: =RANK(J10,$J$3:$J$82,0) -> 50
A11: CUST021 | B11: Sarah Anderson | C11: South | D11: Clothing | E11: 1073.65 | F11: 3 | G11: 0.2 | H11: 45402 | I11: 138.23 | J11: =E11*F11*(1-G11) -> 2576.76 | K11: =TEXT(H11,"mmm-yyyy") -> Apr-2024 | L11: =SUMIFS($J:$J,$K:$K,K11) -> 191711.31 | M11: =IF(L11>L10,"▲",IF(L11<L10,"▼","►")) -> ► | N11: =NOW() -> 46283.658 | O11: =RANK(J11,$J$3:$J$82,0) -> 71
A12: CUST022 | B12: David Brown | C12: Central | D12: Books | E12: 1088.12 | F12: 3 | G12: 0 | H12: 45403 | I12: 140.65 | J12: =E12*F12*(1-G12) -> 3264.36 | K12: =TEXT(H12,"mmm-yyyy") -> Apr-2024 | L12: =SUMIFS($J:$J,$K:$K,K12) -> 191711.31 | M12: =IF(L12>L11,"▲",IF(L12<L11,"▼","►")) -> ► | N12: =NOW() -> 46283.658 | O12: =RANK(J12,$J$3:$J$82,0) -> 65
A13: CUST009 | B13: Linda Jackson | C13: Central | D13: Clothing | E13: 619.14 | F13: 12 | G13: 0 | H13: 45403 | I13: 383.19 | J13: =E13*F13*(1-G13) -> 7429.68 | K13: =TEXT(H13,"mmm-yyyy") -> Apr-2024 | L13: =SUMIFS($J:$J,$K:$K,K13) -> 191711.31 | M13: =IF(L13>L12,"▲",IF(L13<L12,"▼","►")) -> ► | N13: =NOW() -> 46283.658 | O13: =RANK(J13,$J$3:$J$82,0) -> 38
A14: CUST012 | B14: Robert Anderson | C14: West | D14: Clothing | E14: 1316.34 | F14: 4 | G14: 0.05 | H14: 45404 | I14: 258.04 | J14: =E14*F14*(1-G14) -> 5002.092 | K14: =TEXT(H14,"mmm-yyyy") -> Apr-2024 | L14: =SUMIFS($J:$J,$K:$K,K14) -> 191711.31 | M14: =IF(L14>L13,"▲",IF(L14<L13,"▼","►")) -> ► | N14: =NOW() -> 46283.658 | O14: =RANK(J14,$J$3:$J$82,0) -> 53
A15: CUST006 | B15: Mary Jackson | C15: West | D15: Books | E15: 1098.68 | F15: 17 | G15: 0 | H15: 45406 | I15: 1503.15 | J15: =E15*F15*(1-G15) -> 18677.56 | K15: =TEXT(H15,"mmm-yyyy") -> Apr-2024 | L15: =SUMIFS($J:$J,$K:$K,K15) -> 191711.31 | M15: =IF(L15>L14,"▲",IF(L15<L14,"▼","►")) -> ► | N15: =NOW() -> 46283.658 | O15: =RANK(J15,$J$3:$J$82,0) -> 10
... A82: CUST023 | B82: Robert Anderson | C82: West | D82: Electronics | E82: 1291.84 | F82: 15 | G82: 0.2 | H82: 45487 | I82: 1088.93 | J82: =E82*F82*(1-G82) -> 15502.08 | K82: =TEXT(H82,"mmm-yyyy") -> Jul-2024 | L82: =SUMIFS($J:$J,$K:$K,K82) -> 159791.05 | M82: =IF(L82>L81,"▲",IF(L82<L81,"▼","►")) -> ► | N82: =NOW() -> 46283.658 | O82: =RANK(J82,$J$3:$J$82,0) -> 14

Sheet Analysis
A1: Analysis: Pivot Style Summaries + High Value Customers
A3: Region | B3: Total Sales | C3: Total Profit | D3: Orders | F3: Product Category | G3: Total Sales | H3: Total Profit | I3: Orders
A4: Central | B4: =SUMIFS(Dataset!$J$3:$J$82,Dataset!$C$3:$C$82,A4) -> 176891.52 | C4: =SUMIFS(Dataset!$I$3:$I$82,Dataset!$C$3:$C$82,A4) -> 9575.41 | D4: =COUNTIF(Dataset!$C$3:$C$82,A4) -> 22 | F4: Books | G4: =SUMIFS(Dataset!$J$3:$J$82,Dataset!$D$3:$D$82,F4) -> 192139.66 | H4: =SUMIFS(Dataset!$I$3:$I$82,Dataset!$D$3:$D$82,F4) -> 11108.32 | I4: =COUNTIF(Dataset!$D$3:$D$82,F4) -> 21
A5: East | B5: =SUMIFS(Dataset!$J$3:$J$82,Dataset!$C$3:$C$82,A5) -> 102383.14 | C5: =SUMIFS(Dataset!$I$3:$I$82,Dataset!$C$3:$C$82,A5) -> 5697.14 | D5: =COUNTIF(Dataset!$C$3:$C$82,A5) -> 11 | F5: Clothing | G5: =SUMIFS(Dataset!$J$3:$J$82,Dataset!$D$3:$D$82,F5) -> 64435.535 | H5: =SUMIFS(Dataset!$I$3:$I$82,Dataset!$D$3:$D$82,F5) -> 3406.79 | I5: =COUNTIF(Dataset!$D$3:$D$82,F5) -> 11
A6: North | B6: =SUMIFS(Dataset!$J$3:$J$82,Dataset!$C$3:$C$82,A6) -> 33770.739 | C6: =SUMIFS(Dataset!$I$3:$I$82,Dataset!$C$3:$C$82,A6) -> 2254.76 | D6: =COUNTIF(Dataset!$C$3:$C$82,A6) -> 6 | F6: Electronics | G6: =SUMIFS(Dataset!$J$3:$J$82,Dataset!$D$3:$D$82,F6) -> 115896.41 | H6: =SUMIFS(Dataset!$I$3:$I$82,Dataset!$D$3:$D$82,F6) -> 6509.42 | I6: =COUNTIF(Dataset!$D$3:$D$82,F6) -> 14
A7: South | B7: =SUMIFS(Dataset!$J$3:$J$82,Dataset!$C$3:$C$82,A7) -> 187240.56 | C7: =SUMIFS(Dataset!$I$3:$I$82,Dataset!$C$3:$C$82,A7) -> 10569.02 | D7: =COUNTIF(Dataset!$C$3:$C$82,A7) -> 18 | F7: Furniture | G7: =SUMIFS(Dataset!$J$3:$J$82,Dataset!$D$3:$D$82,F7) -> 140645.96 | H7: =SUMIFS(Dataset!$I$3:$I$82,Dataset!$D$3:$D$82,F7) -> 8477.38 | I7: =COUNTIF(Dataset!$D$3:$D$82,F7) -> 12
A8: West | B8: =SUMIFS(Dataset!$J$3:$J$82,Dataset!$C$3:$C$82,A8) -> 207112.1 | C8: =SUMIFS(Dataset!$I$3:$I$82,Dataset!$C$3:$C$82,A8) -> 13207.25 | D8: =COUNTIF(Dataset!$C$3:$C$82,A8) -> 23 | F8: Office Supplies | G8: =SUMIFS(Dataset!$J$3:$J$82,Dataset!$D$3:$D$82,F8) -> 194280.5 | H8: =SUMIFS(Dataset!$I$3:$I$82,Dataset!$D$3:$D$82,F8) -> 11801.67 | I8: =COUNTIF(Dataset!$D$3:$D$82,F8) -> 22
A12: Rank | B12: Customer Name | C12: Customer ID | D12: Total Purchase | E12: Formula Used
A13: =1 -> 1 | B13: =INDEX(Dataset!$B$3:$B$82,MATCH(LARGE(Dataset!$J$3:$J$82,A13),Dataset!$J$3:$J$82,0)) -> James Taylor | C13: =INDEX(Dataset!$A$3:$A$82,MATCH(LARGE(Dataset!$J$3:$J$82,A13),Dataset!$J$3:$J$82,0)) -> CUST017 | D13: =LARGE(Dataset!$J$3:$J$82,A13) -> 25840.57 | E13: ="INDEX + MATCH + LARGE" -> INDEX + MATCH + LARGE
A14: =2 -> 2 | B14: =INDEX(Dataset!$B$3:$B$82,MATCH(LARGE(Dataset!$J$3:$J$82,A14),Dataset!$J$3:$J$82,0)) -> David Brown | C14: =INDEX(Dataset!$A$3:$A$82,MATCH(LARGE(Dataset!$J$3:$J$82,A14),Dataset!$J$3:$J$82,0)) -> CUST022 | D14: =LARGE(Dataset!$J$3:$J$82,A14) -> 25147.982 | E14: ="INDEX + MATCH + LARGE" -> INDEX + MATCH + LARGE
A15: =3 -> 3 | B15: =INDEX(Dataset!$B$3:$B$82,MATCH(LARGE(Dataset!$J$3:$J$82,A15),Dataset!$J$3:$J$82,0)) -> Linda Jackson | C15: =INDEX(Dataset!$A$3:$A$82,MATCH(LARGE(Dataset!$J$3:$J$82,A15),Dataset!$J$3:$J$82,0)) -> CUST009 | D15: =LARGE(Dataset!$J$3:$J$82,A15) -> 23444.1 | E15: ="INDEX + MATCH + LARGE" -> INDEX + MATCH + LARGE
A16: =4 -> 4 | B16: =INDEX(Dataset!$B$3:$B$82,MATCH(LARGE(Dataset!$J$3:$J$82,A16),Dataset!$J$3:$J$82,0)) -> Robert Anderson | C16: =INDEX(Dataset!$A$3:$A$82,MATCH(LARGE(Dataset!$J$3:$J$82,A16),Dataset!$J$3:$J$82,0)) -> CUST005 | D16: =LARGE(Dataset!$J$3:$J$82,A16) -> 23259.391 | E16: ="INDEX + MATCH + LARGE" -> INDEX + MATCH + LARGE
A17: =5 -> 5 | B17: =INDEX(Dataset!$B$3:$B$82,MATCH(LARGE(Dataset!$J$3:$J$82,A17),Dataset!$J$3:$J$82,0)) -> John Brown | C17: =INDEX(Dataset!$A$3:$A$82,MATCH(LARGE(Dataset!$J$3:$J$82,A17),Dataset!$J$3:$J$82,0)) -> CUST008 | D17: =LARGE(Dataset!$J$3:$J$82,A17) -> 22129.56 | E17: ="INDEX + MATCH + LARGE" -> INDEX + MATCH + LARGE
A18: =6 -> 6 | B18: =INDEX(Dataset!$B$3:$B$82,MATCH(LARGE(Dataset!$J$3:$J$82,A18),Dataset!$J$3:$J$82,0)) -> Lisa Thomas | C18: =INDEX(Dataset!$A$3:$A$82,MATCH(LARGE(Dataset!$J$3:$J$82,A18),Dataset!$J$3:$J$82,0)) -> CUST001 | D18: =LARGE(Dataset!$J$3:$J$82,A18) -> 22128.92 | E18: ="INDEX + MATCH + LARGE" -> INDEX + MATCH + LARGE
A19: =7 -> 7 | B19: =INDEX(Dataset!$B$3:$B$82,MATCH(LARGE(Dataset!$J$3:$J$82,A19),Dataset!$J$3:$J$82,0)) -> James Taylor | C19: =INDEX(Dataset!$A$3:$A$82,MATCH(LARGE(Dataset!$J$3:$J$82,A19),Dataset!$J$3:$J$82,0)) -> CUST017 | D19: =LARGE(Dataset!$J$3:$J$82,A19) -> 20644.146 | E19: ="INDEX + MATCH + LARGE" -> INDEX + MATCH + LARGE
A20: =8 -> 8 | B20: =INDEX(Dataset!$B$3:$B$82,MATCH(LARGE(Dataset!$J$3:$J$82,A20),Dataset!$J$3:$J$82,0)) -> Linda Wilson | C20: =INDEX(Dataset!$A$3:$A$82,MATCH(LARGE(Dataset!$J$3:$J$82,A20),Dataset!$J$3:$J$82,0)) -> CUST001 | D20: =LARGE(Dataset!$J$3:$J$82,A20) -> 20405.62 | E20: ="INDEX + MATCH + LARGE" -> INDEX + MATCH + LARGE
A21: =9 -> 9 | B21: =INDEX(Dataset!$B$3:$B$82,MATCH(LARGE(Dataset!$J$3:$J$82,A21),Dataset!$J$3:$J$82,0)) -> Mary Davis | C21: =INDEX(Dataset!$A$3:$A$82,MATCH(LARGE(Dataset!$J$3:$J$82,A21),Dataset!$J$3:$J$82,0)) -> CUST026 | D21: =LARGE(Dataset!$J$3:$J$82,A21) -> 20001.231 | E21: ="INDEX + MATCH + LARGE" -> INDEX + MATCH + LARGE
A22: =10 -> 10 | B22: =INDEX(Dataset!$B$3:$B$82,MATCH(LARGE(Dataset!$J$3:$J$82,A22),Dataset!$J$3:$J$82,0)) -> Mary Jackson | C22: =INDEX(Dataset!$A$3:$A$82,MATCH(LARGE(Dataset!$J$3:$J$82,A22),Dataset!$J$3:$J$82,0)) -> CUST006 | D22: =LARGE(Dataset!$J$3:$J$82,A22) -> 18677.56 | E22: ="INDEX + MATCH + LARGE" -> INDEX + MATCH + LARGE

Sheet Descriptive Stats
A1: Data Analysis ToolPak Style - Descriptive Statistics
A3: Metric | B3: Sales | C3: Profit | D3: Total Purchase
A4: Mean | B4: =AVERAGE(Dataset!$E$3:$E$82) -> 965.6685 | C4: =AVERAGE(Dataset!$I$3:$I$82) -> 516.29475 | D4: =AVERAGE(Dataset!$J$3:$J$82) -> 8842.4758
A5: Median | B5: =MEDIAN(Dataset!$E$3:$E$82) -> 953.325 | C5: =MEDIAN(Dataset!$I$3:$I$82) -> 385.075 | D5: =MEDIAN(Dataset!$J$3:$J$82) -> 6774.8673
A6: Mode | B6: =MODE(Dataset!E2:E81) -> #N/A | C6: =MODE(Dataset!I2:I81) -> #N/A | D6: =MODE(Dataset!J2:J81) -> #N/A
A7: Std Dev | B7: =STDEV(Dataset!E3:E82) -> 360.01431 | C7: =STDEV(Dataset!I3:I82) -> 402.68441 | D7: =STDEV(Dataset!J3:J82) -> 6458.3133
A8: Variance | B8: =VAR(Dataset!E3:E82) -> 129610.3 | C8: =VAR(Dataset!I3:I82) -> 162154.74 | D8: =VAR(Dataset!J3:J82) -> 41709810
A9: Minimum | B9: =MIN(Dataset!$E$3:$E$82) -> 352.11 | C9: =MIN(Dataset!$I$3:$I$82) -> 30.06 | D9: =MIN(Dataset!$J$3:$J$82) -> 688.048
A10: Maximum | B10: =MAX(Dataset!$E$3:$E$82) -> 1593.94 | C10: =MAX(Dataset!$I$3:$I$82) -> 1734.15 | D10: =MAX(Dataset!$J$3:$J$82) -> 25840.57
A11: Range | B11: =MAX(Dataset!$E$3:$E$82)-MIN(Dataset!$E$3:$E$82) -> 1241.83 | C11: =MAX(Dataset!$I$3:$I$82)-MIN(Dataset!$I$3:$I$82) -> 1704.09 | D11: =MAX(Dataset!$J$3:$J$82)-MIN(Dataset!$J$3:$J$82) -> 25152.522
A12: Count | B12: =COUNT(Dataset!$E$3:$E$82) -> 80 | C12: =COUNT(Dataset!$I$3:$I$82) -> 80 | D12: =COUNT(Dataset!$J$3:$J$82) -> 80
A13: Skewness | B13: =SKEW(Dataset!$E$3:$E$82) -> -0.0044937718 | C13: =SKEW(Dataset!$I$3:$I$82) -> 1.2752389 | D13: =SKEW(Dataset!$J$3:$J$82) -> 1.0437507
A14: Kurtosis | B14: =KURT(Dataset!$E$3:$E$82) -> -1.1175309 | C14: =KURT(Dataset!$I$3:$I$82) -> 1.2950201 | D14: =KURT(Dataset!$J$3:$J$82) -> 0.21776498

Sheet Regression
A1: Linear Regression: Profit vs Sales
A3: Regression Metric | B3: Value
A4: R Square | B4: =RSQ(Dataset!$I$3:$I$82,Dataset!$E$3:$E$82) -> 0.24107796
A5: Correlation | B5: =CORREL(Dataset!$I$3:$I$82,Dataset!$E$3:$E$82) -> 0.49099691
A6: Slope | B6: =SLOPE(Dataset!$I$3:$I$82,Dataset!$E$3:$E$82) -> 0.54919151
A7: Intercept | B7: =INTERCEPT(Dataset!$I$3:$I$82,Dataset!$E$3:$E$82) -> -14.042188
A8: Regression Equation | B8: ="Profit = "&ROUND(B6,4)&" * Sales + "&ROUND(B7,2) -> Profit = 0.5492 * Sales + -14.04
A11: Sales | B11: Profit
A12: =Dataset!E3 -> 716.88 | B12: =Dataset!I3 -> 348.83
A13: =Dataset!E4 -> 1478.05 | B13: =Dataset!I4 -> 733.78
A14: =Dataset!E5 -> 1570.26 | B14: =Dataset!I5 -> 383.24
A15: =Dataset!E6 -> 731.49 | B15: =Dataset!I6 -> 414.77
A16: =Dataset!E7 -> 1360.03 | B16: =Dataset!I7 -> 1702.95
A17: =Dataset!E8 -> 945.99 | B17: =Dataset!I8 -> 1328.83
A18: =Dataset!E9 -> 438.74 | B18: =Dataset!I9 -> 99.07
A19: =Dataset!E10 -> 407.77 | B19: =Dataset!I10 -> 308.05
A20: =Dataset!E11 -> 1073.65 | B20: =Dataset!I11 -> 138.23
A21: =Dataset!E12 -> 1088.12 | B21: =Dataset!I12 -> 140.65
A22: =Dataset!E13 -> 619.14 | B22: =Dataset!I13 -> 383.19
A23: =Dataset!E14 -> 1316.34 | B23: =Dataset!I14 -> 258.04
... A91: =Dataset!E82 -> 1291.84 | B91: =Dataset!I82 -> 1088.93

Sheet What-If
A1: WHAT-IF Analysis: Impact of Discount on Profit
A3: Input / Output | B3: Value | D3: Discount % | E3: Estimated Profit
A4: Base Sales | B4: =AVERAGE(Dataset!$E$3:$E$82) -> 965.6685 | D4: 0 | E4: =$B$4*$B$5*(1-D4)-($B$4*$B$5*$B$6) -> 2889.763
A5: Base Quantity | B5: =AVERAGE(Dataset!$F$3:$F$82) -> 9.975 | D5: 0.05 | E5: =$B$4*$B$5*(1-D5)-($B$4*$B$5*$B$6) -> 2408.1358
A6: Cost Ratio | B6: 0.7 | D6: 0.1 | E6: =$B$4*$B$5*(1-D6)-($B$4*$B$5*$B$6) -> 1926.5087
A7: Discount % | B7: 0.1 | D7: 0.15 | E7: =$B$4*$B$5*(1-D7)-($B$4*$B$5*$B$6) -> 1444.8815
A8: Estimated Profit | B8: =B4*B5*(1-B7)-(B4*B5*B6) -> 1926.5087 | D8: 0.2 | E8: =$B$4*$B$5*(1-D8)-($B$4*$B$5*$B$6) -> 963.25433
D9: 0.25 | E9: =$B$4*$B$5*(1-D9)-($B$4*$B$5*$B$6) -> 481.62716
D10: 0.3 | E10: =$B$4*$B$5*(1-D10)-($B$4*$B$5*$B$6) -> 0

Sheet Dashboard
A1: PR. 2 Analyzer Dashboard
A3: KPI | B3: Value | D3: Region | E3: Total Sales | F3: Total Profit | G3: Orders | I3: Product Category | J3: Total Sales | K3: Total Profit | L3: Orders
A4: Total Sales | B4: =SUM(Dataset!$J$3:$J$82) -> 707398.06 | D4: Central | E4: =SUMIFS(Dataset!$J$3:$J$82,Dataset!$C$3:$C$82,D4) -> 176891.52 | F4: =SUMIFS(Dataset!$I$3:$I$82,Dataset!$C$3:$C$82,D4) -> 9575.41 | G4: =COUNTIF(Dataset!$C$3:$C$82,D4) -> 22 | I4: Books | J4: =SUMIFS(Dataset!$J$3:$J$82,Dataset!$D$3:$D$82,I4) -> 192139.66 | K4: =SUMIFS(Dataset!$I$3:$I$82,Dataset!$D$3:$D$82,I4) -> 11108.32 | L4: =COUNTIF(Dataset!$D$3:$D$82,I4) -> 21
A5: Total Profit | B5: =SUM(Dataset!$I$3:$I$82) -> 41303.58 | D5: East | E5: =SUMIFS(Dataset!$J$3:$J$82,Dataset!$C$3:$C$82,D5) -> 102383.14 | F5: =SUMIFS(Dataset!$I$3:$I$82,Dataset!$C$3:$C$82,D5) -> 5697.14 | G5: =COUNTIF(Dataset!$C$3:$C$82,D5) -> 11 | I5: Clothing | J5: =SUMIFS(Dataset!$J$3:$J$82,Dataset!$D$3:$D$82,I5) -> 64435.535 | K5: =SUMIFS(Dataset!$I$3:$I$82,Dataset!$D$3:$D$82,I5) -> 3406.79 | L5: =COUNTIF(Dataset!$D$3:$D$82,I5) -> 11
A6: Total Orders | B6: =COUNTA(Dataset!$A$3:$A$82) -> 80 | D6: North | E6: =SUMIFS(Dataset!$J$3:$J$82,Dataset!$C$3:$C$82,D6) -> 33770.739 | F6: =SUMIFS(Dataset!$I$3:$I$82,Dataset!$C$3:$C$82,D6) -> 2254.76 | G6: =COUNTIF(Dataset!$C$3:$C$82,D6) -> 6 | I6: Electronics | J6: =SUMIFS(Dataset!$J$3:$J$82,Dataset!$D$3:$D$82,I6) -> 115896.41 | K6: =SUMIFS(Dataset!$I$3:$I$82,Dataset!$D$3:$D$82,I6) -> 6509.42 | L6: =COUNTIF(Dataset!$D$3:$D$82,I6) -> 14
A7: Best Region | B7: =INDEX(Analysis!$A$4:$A$8,MATCH(MAX(Analysis!$B$4:$B$8),Analysis!$B$4:$B$8,0)) -> West | D7: South | E7: =SUMIFS(Dataset!$J$3:$J$82,Dataset!$C$3:$C$82,D7) -> 187240.56 | F7: =SUMIFS(Dataset!$I$3:$I$82,Dataset!$C$3:$C$82,D7) -> 10569.02 | G7: =COUNTIF(Dataset!$C$3:$C$82,D7) -> 18 | I7: Furniture | J7: =SUMIFS(Dataset!$J$3:$J$82,Dataset!$D$3:$D$82,I7) -> 140645.96 | K7: =SUMIFS(Dataset!$I$3:$I$82,Dataset!$D$3:$D$82,I7) -> 8477.38 | L7: =COUNTIF(Dataset!$D$3:$D$82,I7) -> 12
A8: Top Customer | B8: =Analysis!B13 -> James Taylor | D8: West | E8: =SUMIFS(Dataset!$J$3:$J$82,Dataset!$C$3:$C$82,D8) -> 207112.1 | F8: =SUMIFS(Dataset!$I$3:$I$82,Dataset!$C$3:$C$82,D8) -> 13207.25 | G8: =COUNTIF(Dataset!$C$3:$C$82,D8) -> 23 | I8: Office Supplies | J8: =SUMIFS(Dataset!$J$3:$J$82,Dataset!$D$3:$D$82,I8) -> 194280.5 | K8: =SUMIFS(Dataset!$I$3:$I$82,Dataset!$D$3:$D$82,I8) -> 11801.67 | L8: =COUNTIF(Dataset!$D$3:$D$82,I8) -> 22
